README.rst
setup.py
./vice/src/callback.c
./vice/src/imf.c
./vice/src/stats.c
./vice/src/utils.c
./vice/src/dataframe/calclogz.c
./vice/src/dataframe/calclookback.c
./vice/src/dataframe/calcz.c
./vice/src/dataframe/fromfile.c
./vice/src/dataframe/history.c
./vice/src/dataframe/utils.c
./vice/src/io/agb.c
./vice/src/io/ccsne.c
./vice/src/io/singlezone.c
./vice/src/io/sneia.c
./vice/src/io/utils.c
./vice/src/io/tests/_agb.c
./vice/src/io/tests/_ccsne.c
./vice/src/io/tests/_sneia.c
./vice/src/io/tests/_utils.c
./vice/src/io/tests/agb.c
./vice/src/io/tests/ccsne.c
./vice/src/io/tests/sneia.c
./vice/src/io/tests/utils.c
./vice/src/objects/agb.c
./vice/src/objects/callback_1arg.c
./vice/src/objects/callback_2arg.c
./vice/src/objects/ccsne.c
./vice/src/objects/channel.c
./vice/src/objects/element.c
./vice/src/objects/fromfile.c
./vice/src/objects/imf.c
./vice/src/objects/integral.c
./vice/src/objects/ism.c
./vice/src/objects/mdf.c
./vice/src/objects/singlezone.c
./vice/src/objects/sneia.c
./vice/src/objects/ssp.c
./vice/src/objects/tests/agb.c
./vice/src/objects/tests/callback_1arg.c
./vice/src/objects/tests/callback_2arg.c
./vice/src/objects/tests/ccsne.c
./vice/src/objects/tests/channel.c
./vice/src/objects/tests/element.c
./vice/src/objects/tests/fromfile.c
./vice/src/objects/tests/imf.c
./vice/src/objects/tests/integral.c
./vice/src/objects/tests/ism.c
./vice/src/objects/tests/mdf.c
./vice/src/objects/tests/singlezone.c
./vice/src/objects/tests/sneia.c
./vice/src/objects/tests/ssp.c
./vice/src/singlezone/agb.c
./vice/src/singlezone/ccsne.c
./vice/src/singlezone/channel.c
./vice/src/singlezone/element.c
./vice/src/singlezone/ism.c
./vice/src/singlezone/mdf.c
./vice/src/singlezone/recycling.c
./vice/src/singlezone/singlezone.c
./vice/src/singlezone/sneia.c
./vice/src/singlezone/tests/_singlezone.c
./vice/src/singlezone/tests/agb.c
./vice/src/singlezone/tests/ccsne.c
./vice/src/singlezone/tests/element.c
./vice/src/singlezone/tests/ism.c
./vice/src/singlezone/tests/mdf.c
vice.egg-info/PKG-INFO
vice.egg-info/SOURCES.txt
vice.egg-info/dependency_links.txt
vice.egg-info/not-zip-safe
vice.egg-info/top_level.txt
