Metadata-Version: 1.2
Name: vice
Version: 1.1.0
Summary: Galactic Chemical Evolution Integrator
Home-page: http://github.com/giganano/VICE.git
Author: James W. Johnson
Author-email: giganano9@gmail.com
Maintainer: James W. Johnson
Maintainer-email: giganano9@gmail.com
License: MIT
Keywords: galaxies,simulations,abundances
Platform: Linux
Platform: Mac OS X
Platform: Unix
Classifier: Development Status :: 5 - Production/Stable 
Classifier: Intended Audience :: Science/Research 
Classifier: License :: OSI Approved :: MIT License 
Classifier: Natural Language :: English 
Classifier: Operating System :: MacOS 
Classifier: Operating System :: POSIX 
Classifier: Operating System :: Unix 
Classifier: Programming Language :: C 
Classifier: Programming Language :: Cython 
Classifier: Programming Language :: Python 
Classifier: Programming Language :: Python :: 3  
Classifier: Programming Language :: Python :: 3.5 
Classifier: Programming Language :: Python :: 3.6 
Classifier: Programming Language :: Python :: 3.7 
Classifier: Programming Language :: Python :: 3.8 
Classifier: Programming Language :: Python :: 3 :: Only 
Classifier: Programming Language :: Python :: Implementation :: CPython 
Classifier: Topic :: Scientific/Engineering
Classifier: Topic :: Scientific/Engineering :: Astronomy 
Classifier: Topic :: Scientific/Engineering :: Physics
Classifier: 
Provides: vice
Requires-Python: >=3.5.*, <4
